expiry/__init__.py
expiry/apps.py
expiry/middleware.py
expiry/rules.py
expiry/signals.py
django_expiry-0.2.3.dist-info/AUTHORS
django_expiry-0.2.3.dist-info/LICENSE
django_expiry-0.2.3.dist-info/METADATA
django_expiry-0.2.3.dist-info/WHEEL
django_expiry-0.2.3.dist-info/top_level.txt
django_expiry-0.2.3.dist-info/RECORD
